<?xml version="1.0" encoding="UTF-8"?>
<!DOCTYPE suite SYSTEM "http://testng.org/testng-1.0.dtd" >

<suite name="测试" verbose="1">

    <test name="安全可信网关">
        <parameter name="DriverName" value="chrome" />
        <parameter name="ChromeDriverPath" value=".\src\main\resources\chromedriver.exe"/>
        <parameter name="SPG_URl" value="https://172.20.52.115"/>
        <parameter name="Username" value="secadmin"/>
        <parameter name="passwd" value="sailing2018!"/>
        <classes>
            <class name="webTest.DemoTest"></class>
        </classes>
    </test>

</suite>